mkdocs_run_shell_cmd_plugin/__init__.py
mkdocs_run_shell_cmd_plugin/plugin.py
mkdocs_run_shell_cmd_plugin-0.2.0.dist-info/LICENSE.txt
mkdocs_run_shell_cmd_plugin-0.2.0.dist-info/METADATA
mkdocs_run_shell_cmd_plugin-0.2.0.dist-info/WHEEL
mkdocs_run_shell_cmd_plugin-0.2.0.dist-info/entry_points.txt
mkdocs_run_shell_cmd_plugin-0.2.0.dist-info/RECORD
