Metadata-Version: 2.1
Name: mkdocs-run-shell-cmd-plugin
Version: 0.2.0
Summary: MkDocs plugin to run a specified command or commands and include the output in the generated site.
Home-page: https://seapagan.github.io/mkdocs-run-shell-cmd-plugin/
Author: Grant Ramsay
Author-email: seapagan@gmail.com
Requires-Python: >=3.8.1,<4.0.0
Classifier: Development Status :: 4 - Beta
Classifier: Environment :: Web Environment
Classifier: Intended Audience :: Developers
Classifier: License :: OSI Approved :: MIT License
Classifier: Operating System :: OS Independent
Classifier: Programming Language :: Python :: 3
Classifier: Programming Language :: Python :: 3.9
Classifier: Programming Language :: Python :: 3.10
Classifier: Programming Language :: Python :: 3.11
Classifier: Programming Language :: Python :: 3.12
Classifier: Programming Language :: Python :: 3.8
Classifier: Topic :: Documentation
Classifier: Topic :: Software Development :: Libraries
Classifier: Topic :: Software Development :: Libraries :: Python Modules
Classifier: Topic :: Text Processing :: Markup :: Markdown
Requires-Dist: mkdocs (>=1.4.3,<2.0.0)
Requires-Dist: rich (>=13.4.2,<14.0.0)
Project-URL: Bug Tracker, https://github.com/seapagan/mkdocs-run-shell-cmd-plugin/issues
Project-URL: Pull Requests, https://github.com/seapagan/mkdocs-run-shell-cmd-plugin/pulls
Project-URL: Repository, https://github.com/seapagan/mkdocs-run-shell-cmd-plugin
